string_similarity/__init__.py
string_similarity/example.py
string_similarity/string_similarity.py
string_similarity/extensions/string_extension.py
string_similarity/models/best_match.py
string_similarity/models/rating.py
string_similarity-0.0.2.dist-info/LICENSE
string_similarity-0.0.2.dist-info/METADATA
string_similarity-0.0.2.dist-info/WHEEL
string_similarity-0.0.2.dist-info/top_level.txt
string_similarity-0.0.2.dist-info/RECORD
