Metadata-Version: 2.1
Name: string_similarity
Version: 0.0.2
Summary: Finds degree of similarity between two strings, based on Dice's Coefficient, which is mostly better than Levenshtein distance.
Author-email: Malay Patel <malayp.dev@gmail.com>
Project-URL: Homepage, https://github.com/Malay1121/string-similarity
Project-URL: Bug Tracker, https://github.com/Malay1121/string-similarity/issues
Classifier: Programming Language :: Python :: 3
Classifier: License :: OSI Approved :: MIT License
Classifier: Operating System :: OS Independent
Requires-Python: >=3.11
License-File: LICENSE
